freetail_gnuradio/VERSION
freetail_gnuradio/__init__.py
freetail_gnuradio/freetail_module.py
freetail_gnuradio/pulse_integrator.py
freetail_gnuradio/save_echo_file.py
freetail_gnuradio/signal_noise_histogram.py
freetail_gnuradio/split_gate_tracker.py
freetail_gnuradio/target_histogram.py
freetail_gnuradio/waveforms.py
freetail_gnuradio/grc/freetail_module.block.yml
freetail_gnuradio/grc/pulse_integrator.block.yml
freetail_gnuradio/grc/save_echo_file.block.yml
freetail_gnuradio/grc/signal_noise_histrogram.block.yml
freetail_gnuradio/grc/split_gate_tracker.block.yml
freetail_gnuradio/grc/target_histrogram.block.yml
Freetail_GNURadio-0.2.2.dist-info/LICENSE
Freetail_GNURadio-0.2.2.dist-info/METADATA
Freetail_GNURadio-0.2.2.dist-info/WHEEL
Freetail_GNURadio-0.2.2.dist-info/top_level.txt
Freetail_GNURadio-0.2.2.dist-info/RECORD
