Metadata-Version: 2.1
Name: Freetail-GNURadio
Version: 0.2.2
Summary: GNU Radio Blocks for the Freetail ultrasonic module
Home-page: https://github.com/DavidPowell/Freetail-GNURadio
Author: David A. Powell
Author-email: david.powell@adfa.edu.au
License: UNKNOWN
Platform: UNKNOWN
Classifier: Intended Audience :: Education
Classifier: License :: OSI Approved :: GNU General Public License v3 (GPLv3)
Classifier: Topic :: Scientific/Engineering
Classifier: Programming Language :: Python :: 3.8
Requires-Dist: numpy
Requires-Dist: matplotlib
Requires-Dist: scipy
Requires-Dist: pyserial
